t87s/__init__.py
t87s/duration.py
t87s/primitives.py
t87s/py.typed
t87s/query_cache.py
t87s/schema.py
t87s/typed_tag.py
t87s/types.py
t87s/adapters/__init__.py
t87s/adapters/base.py
t87s/adapters/cloud.py
t87s/adapters/memory.py
t87s/adapters/redis.py
t87s/adapters/upstash.py
t87s-0.1.1.dist-info/METADATA
t87s-0.1.1.dist-info/WHEEL
t87s-0.1.1.dist-info/RECORD
